<?xml version="1.0" encoding="UTF-8"?>
<out>
   <result initial="11" final="12"/>
   <result initial="17" final="18"/>
   <result initial="25" final="26"/>
   <result initial="35" final="0"/>
   <result initial="47" final="48"/>
   <result initial="61" final="62"/>
   <result initial="77" final="0"/>
   <result initial="95" final="96"/>
   <result initial="15" final="16"/>
   <result initial="37" final="38"/>
   <result initial="61" final="62"/>
   <result initial="87" final="88"/>
   <result initial="15" final="16"/>
   <result initial="45" final="46"/>
   <result initial="77" final="0"/>
   <result initial="11" final="12"/>
   <result initial="47" final="48"/>
   <result initial="85" final="86"/>
   <result initial="25" final="26"/>
   <result initial="67" final="68"/>
   <result initial="11" final="12"/>
   <result initial="57" final="58"/>
   <result initial="5" final="6"/>
   <result initial="55" final="56"/>
   <result initial="7" final="0"/>
   <result initial="61" final="62"/>
   <result initial="17" final="18"/>
   <result initial="75" final="76"/>
   <result initial="35" final="0"/>
   <result initial="97" final="98"/>
   <result initial="61" final="62"/>
   <result initial="27" final="28"/>
   <result initial="95" final="96"/>
   <result initial="65" final="66"/>
   <result initial="37" final="38"/>
   <result initial="11" final="12"/>
   <result initial="87" final="88"/>
   <result initial="65" final="66"/>
   <result initial="45" final="46"/>
   <result initial="27" final="28"/>
   <result initial="11" final="12"/>
   <result initial="97" final="98"/>
   <result initial="85" final="86"/>
   <result initial="75" final="76"/>
   <result initial="67" final="68"/>
   <result initial="61" final="62"/>
   <result initial="57" final="58"/>
   <result initial="55" final="56"/>
   <result initial="55" final="56"/>
   <result initial="57" final="58"/>
   <result initial="61" final="62"/>
   <result initial="67" final="68"/>
   <result initial="75" final="76"/>
   <result initial="85" final="86"/>
   <result initial="97" final="98"/>
   <result initial="11" final="12"/>
   <result initial="27" final="28"/>
   <result initial="45" final="46"/>
   <result initial="65" final="66"/>
   <result initial="87" final="88"/>
   <result initial="11" final="12"/>
   <result initial="37" final="38"/>
   <result initial="65" final="66"/>
   <result initial="95" final="96"/>
   <result initial="27" final="28"/>
   <result initial="61" final="62"/>
   <result initial="97" final="98"/>
   <result initial="35" final="0"/>
   <result initial="75" final="76"/>
   <result initial="17" final="18"/>
   <result initial="61" final="62"/>
   <result initial="7" final="0"/>
   <result initial="55" final="56"/>
   <result initial="5" final="6"/>
   <result initial="57" final="58"/>
   <result initial="11" final="12"/>
   <result initial="67" final="68"/>
   <result initial="25" final="26"/>
   <result initial="85" final="86"/>
   <result initial="47" final="48"/>
   <result initial="11" final="12"/>
   <result initial="77" final="0"/>
   <result initial="45" final="46"/>
   <result initial="15" final="16"/>
   <result initial="87" final="88"/>
   <result initial="61" final="62"/>
   <result initial="37" final="38"/>
   <result initial="15" final="16"/>
   <result initial="95" final="96"/>
   <result initial="77" final="0"/>
   <result initial="61" final="62"/>
   <result initial="47" final="48"/>
   <result initial="35" final="0"/>
   <result initial="25" final="26"/>
   <result initial="17" final="18"/>
   <result initial="11" final="12"/>
   <result initial="7" final="0"/>
   <result initial="5" final="6"/>
   <result initial="5" final="6"/>
   <result initial="7" final="0"/>
</out>
