<?xml version="1.0" ?><testResults driver="Saxon-6" on="2014-03-28T15:25:14" baseline="no"><test name="musicxml-tests-001" run="success" buildTime="17.99730595" compileTime="7.2064145" transformTime="101.76236035"/><test name="musicxml-tests-002" run="success" buildTime="3.69552265" compileTime="2.5418858" transformTime="20.9143554"/><test name="musicxml-tests-003" run="success" buildTime="2.71574095" compileTime="3.86622195" transformTime="42.2875689"/><test name="musicxml-tests-004" run="success" buildTime="1.84677345" compileTime="3.80528525" transformTime="16.36002555"/><test name="xsltmark-alphabetize" run="success" buildTime="0.61631815" compileTime="1.234381" transformTime="18.68946755"/><test name="xsltmark-attsets" run="success" buildTime="0.2637332" compileTime="1.142168" transformTime="2.96990385"/><test name="xsltmark-avts" run="success" buildTime="0.60826165" compileTime="1.0635537" transformTime="3.24536255"/><test name="xsltmark-axis" run="success" buildTime="0.2686595" compileTime="1.8896471" transformTime="2.1016037"/><test name="xsltmark-backwards" run="success" buildTime="0.2967287" compileTime="1.0409751" transformTime="7.01003225"/><test name="xsltmark-bottles" run="success" buildTime="0.24628605" compileTime="1.53619" transformTime="7.46611945"/><test name="xsltmark-breadth" run="success" buildTime="0.3453753" compileTime="1.0797177" transformTime="3.19307255"/><test name="xsltmark-brutal" run="success" buildTime="0.26832595" compileTime="2.2812058" transformTime="5.9544323"/><test name="xsltmark-chart" run="success" buildTime="0.2939064" compileTime="2.10596535" transformTime="4.53821685"/><test name="xsltmark-creation" run="success" buildTime="0.69457355" compileTime="1.3839129" transformTime="5.74847975"/><test name="xsltmark-current" run="success" buildTime="0.2322772" compileTime="1.0644773" transformTime="1.8377165"/><test name="xsltmark-dbonerow" run="success" buildTime="44.07204635" compileTime="1.4902373" transformTime="86.6169596"/><test name="xsltmark-dbtail" run="success" buildTime="0.5940474" compileTime="0.90637585" transformTime="3.63815275"/><test name="xsltmark-decoy" run="success" buildTime="0.61549715" compileTime="1.4554201" transformTime="9.8533677"/><test name="xsltmark-depth" run="success" buildTime="0.3391406" compileTime="0.9230531" transformTime="3.84733805"/><test name="xsltmark-encrypt" run="success" buildTime="0.6488262" compileTime="0.9487621" transformTime="6.03173825"/><test name="xsltmark-functions" run="success" buildTime="0.62109035" compileTime="1.11112245" transformTime="9.8175496"/><test name="xsltmark-game" run="success" buildTime="0.26257835" compileTime="0.94434895" transformTime="1.83468875"/><test name="xsltmark-html" run="success" buildTime="0.2191917" compileTime="0.9059141" transformTime="1.6849261"/><test name="xsltmark-identity" run="success" buildTime="4.01259795" compileTime="0.78168055" transformTime="13.754304"/><test name="xsltmark-inventory" run="success" buildTime="0.2673764" compileTime="0.90534965" transformTime="2.35012185"/><test name="xsltmark-metric" run="success" buildTime="0.2407698" compileTime="1.00005135" transformTime="2.5680052"/><test name="xsltmark-number" run="success" buildTime="0.209519" compileTime="1.259782" transformTime="2.4433866"/><test name="xsltmark-oddtemplate" run="success" buildTime="0.21547135" compileTime="1.0122898" transformTime="1.76697875"/><test name="xsltmark-patterns" run="success" buildTime="0.6124695" compileTime="1.05036555" transformTime="4.431687"/><test name="xsltmark-prettyprint" run="success" buildTime="0.6445414" compileTime="1.39073775" transformTime="27.14055165"/><test name="xsltmark-priority" run="success" buildTime="0.23479165" compileTime="1.06057725" transformTime="2.25234115"/><test name="xsltmark-products" run="success" buildTime="0.2725592" compileTime="0.91186665" transformTime="2.8695573"/><test name="xsltmark-queens" run="success" buildTime="0.21962785" compileTime="2.3017833" transformTime="17.2322002"/><test name="xsltmark-reverser" run="success" buildTime="0.25867865" compileTime="0.9793972" transformTime="4.55081455"/><test name="xsltmark-stringsort" run="success" buildTime="4.24882615" compileTime="0.8424888" transformTime="21.30211675"/><test name="xsltmark-summarize" run="success" buildTime="0.33339315" compileTime="0.87792165" transformTime="2.36610625"/><test name="xsltmark-total" run="success" buildTime="0.21872985" compileTime="0.79935865" transformTime="1.7026042"/><test name="xsltmark-tower" run="success" buildTime="0.20682495" compileTime="1.2308915" transformTime="8.74106435"/><test name="xsltmark-trend" run="success" buildTime="0.25054525" compileTime="0.84964725" transformTime="5.94796655"/><test name="xsltmark-union" run="success" buildTime="0.20128295" compileTime="0.93688265" transformTime="1.8761516"/><test name="xsltmark-xpath" run="success" buildTime="0.2049262" compileTime="0.84592685" transformTime="1.8982425"/><test name="xsltmark-xslbench1" run="success" buildTime="0.23943545" compileTime="1.130186" transformTime="1.6020525"/><test name="xsltmark-xslbench2" run="success" buildTime="2.06001285" compileTime="0.89898655" transformTime="9.4578576"/><test name="xsltmark-xslbench3" run="success" buildTime="2.00764585" compileTime="0.81229" transformTime="9.6302758"/><test name="xmark-q1-1" run="success" buildTime="11.491982" compileTime="0.7611546" transformTime="18.2064656"/><test name="xmark-q1-4" run="success" buildTime="46.74966005" compileTime="0.72697875" transformTime="71.2839255"/><test name="xmark-q2-1" run="success" buildTime="11.6181142" compileTime="0.7284669" transformTime="20.48338695"/><test name="xmark-q2-4" run="success" buildTime="46.854009" compileTime="0.72053885" transformTime="76.149891"/><test name="xmark-q3-1" run="success" buildTime="11.6722515" compileTime="0.7674151" transformTime="19.7031685"/><test name="xmark-q3-4" run="success" buildTime="47.229968" compileTime="0.7651316" transformTime="70.5386531"/><test name="xmark-q5-1" run="success" buildTime="11.81613865" compileTime="0.74473385" transformTime="17.73767795"/><test name="xmark-q5-4" run="success" buildTime="46.4992433" compileTime="0.70955745" transformTime="68.7067608"/><test name="xmark-q6-1" run="success" buildTime="11.401052" compileTime="0.7211803" transformTime="19.0008468"/><test name="xmark-q6-4" run="success" buildTime="46.3510455" compileTime="0.7430148" transformTime="72.8384093"/><test name="xmark-q7-1" run="success" buildTime="11.31204625" compileTime="0.74819755" transformTime="18.47912785"/><test name="xmark-q7-4" run="success" buildTime="46.5548684" compileTime="0.7365748" transformTime="70.96851815"/><test name="xmark-q8-1" run="success" buildTime="11.4158307" compileTime="0.7642591" transformTime="35.1144582"/><test name="xmark-q8-4" run="success" buildTime="46.04849265" compileTime="0.77154595" transformTime="291.91181525"/><test name="xmark-q11-1" run="success" buildTime="11.597665" compileTime="0.7468375" transformTime="45.03222565"/><test name="xmark-q11-4" run="success" buildTime="45.99153305" compileTime="0.75802445" transformTime="443.89557415"/><test name="xmark-q12-1" run="success" buildTime="11.302399" compileTime="0.79525325" transformTime="24.7396279"/><test name="xmark-q12-4" run="success" buildTime="46.23558705" compileTime="0.7618988" transformTime="145.2361"/><test name="xmark-q13-1" run="success" buildTime="11.4659141" compileTime="0.7332137" transformTime="18.3134061"/><test name="xmark-q13-4" run="success" buildTime="46.20659375" compileTime="0.73139195" transformTime="69.32813345"/><test name="xmark-q14-1" run="success" buildTime="11.6275048" compileTime="0.7234381" transformTime="22.962181"/><test name="xmark-q14-4" run="success" buildTime="46.1541502" compileTime="0.7534573" transformTime="87.9642078"/><test name="xmark-q15-1" run="success" buildTime="11.49223865" compileTime="0.71202055" transformTime="18.68882625"/><test name="xmark-q15-4" run="success" buildTime="45.90532385" compileTime="0.7335729" transformTime="68.50427175"/><test name="xmark-q16-1" run="success" buildTime="11.41051965" compileTime="0.7201027" transformTime="17.93277735"/><test name="xmark-q16-4" run="success" buildTime="46.197229" compileTime="0.716639" transformTime="68.29731895"/><test name="xmark-q17-1" run="success" buildTime="11.3535856" compileTime="0.72271975" transformTime="18.48395125"/><test name="xmark-q17-4" run="success" buildTime="46.35073765" compileTime="0.7252341" transformTime="68.4421295"/><test name="xmark-q18-1" run="success" buildTime="11.38180895" compileTime="0.7263373" transformTime="18.01606155"/><test name="xmark-q18-4" run="success" buildTime="45.8583963" compileTime="0.71779345" transformTime="68.67302125"/><test name="xmark-q19-1" run="success" buildTime="11.42581155" compileTime="0.77421425" transformTime="19.76431055"/><test name="xmark-q19-4" run="success" buildTime="46.0536755" compileTime="0.7603334" transformTime="85.1048364"/><test name="xmark-q20-1" run="success" buildTime="11.5936113" compileTime="0.7573061" transformTime="18.2312507"/><test name="xmark-q20-4" run="success" buildTime="46.2201669" compileTime="0.7640026" transformTime="69.31669015"/></testResults>